ccguard/__init__.py
ccguard/ccguard.py
ccguard/ccguard_convert.py
ccguard/ccguard_diff.py
ccguard/ccguard_log.py
ccguard/ccguard_server.py
ccguard/ccguard_server_blueprints.py
ccguard/ccguard_show.py
ccguard/ccguard_sync.py
ccguard/test_ccguard.py
ccguard/test_ccguard_convert.py
ccguard/test_ccguard_diff.py
ccguard/test_ccguard_log.py
ccguard/test_ccguard_server.py
ccguard/test_ccguard_show.py
ccguard/test_ccguard_sync.py
ccguard/test_normalize_paths.py
ccguard/test_web_adapter.py
ccguard/scripts/cleanup_database.py
ccguard/scripts/migrate_sqlite_database.py
ccguard/templates/index.html
ccguard-0.7.2.dist-info/LICENSE.txt
ccguard-0.7.2.dist-info/METADATA
ccguard-0.7.2.dist-info/WHEEL
ccguard-0.7.2.dist-info/entry_points.txt
ccguard-0.7.2.dist-info/top_level.txt
ccguard-0.7.2.dist-info/RECORD
