Metadata-Version: 2.1
Name: ccguard
Version: 0.7.2
Summary: Prevent code coverage regressions
Home-page: https://github.com/nilleb/ccguard
Author: Ivo Bellin Salarin
Author-email: me@nilleb.com
License: UNKNOWN
Platform: UNKNOWN
Classifier: Programming Language :: Python :: 3
Classifier: License :: OSI Approved :: GNU Affero General Public License v3 or later (AGPLv3+)
Classifier: Operating System :: OS Independent
Requires-Dist: pycobertura (==0.10.5)
Requires-Dist: gitpython
Requires-Dist: flask
Requires-Dist: requests
Requires-Dist: lxml
Requires-Dist: colour
